O_NLP_Preprocessor/Lemmatizer.py
O_NLP_Preprocessor/Stem.py
O_NLP_Preprocessor/Stopwords.py
O_NLP_Preprocessor/Tokenize.py
O_NLP_Preprocessor/__init__.py
O_NLP_Preprocessor_Emeka_Onyebuchi-0.0.2.dist-info/LICENSE.txt
O_NLP_Preprocessor_Emeka_Onyebuchi-0.0.2.dist-info/METADATA
O_NLP_Preprocessor_Emeka_Onyebuchi-0.0.2.dist-info/WHEEL
O_NLP_Preprocessor_Emeka_Onyebuchi-0.0.2.dist-info/top_level.txt
O_NLP_Preprocessor_Emeka_Onyebuchi-0.0.2.dist-info/RECORD
